CHANGELOG.md
scw_serverless/__init__.py
scw_serverless/app.py
scw_serverless/cli.py
scw_serverless/config/__init__.py
scw_serverless/config/function.py
scw_serverless/config/route.py
scw_serverless/config/triggers.py
scw_serverless/dependencies_manager.py
scw_serverless/deployment/__init__.py
scw_serverless/deployment/api_wrapper.py
scw_serverless/deployment/client.py
scw_serverless/deployment/deployment_manager.py
scw_serverless/deployment/exceptions.py
scw_serverless/deployment/runtime.py
scw_serverless/gateway/__init__.py
scw_serverless/gateway/gateway_manager.py
scw_serverless/gateway/serverless_gateway.py
scw_serverless/loader.py
scw_serverless/local_app.py
scw_serverless/logger.py
scw_serverless/utils/__init__.py
scw_serverless/utils/files.py
scw_serverless/utils/string.py
scw_serverless-1.2.0.dist-info/METADATA
scw_serverless-1.2.0.dist-info/entry_points.txt
scw_serverless-1.2.0.dist-info/WHEEL
scw_serverless-1.2.0.dist-info/LICENSE
scw_serverless-1.2.0.dist-info/RECORD
