Metadata-Version: 2.1
Name: scw-serverless
Version: 1.2.0
Summary: Framework for writing serverless APIs in Python, using Scaleway functions and containers.
Home-page: https://github.com/scaleway/serverless-api-framework-python
License: MIT
Keywords: serverless,scaleway,functions,cloud,faas
Author: Scaleway Serverless Team
Author-email: opensource@scaleway.com
Requires-Python: >=3.10,<3.12
Classifier: Development Status :: 4 - Beta
Classifier: Intended Audience :: Developers
Classifier: Intended Audience :: Information Technology
Classifier: License :: OSI Approved :: MIT License
Classifier: Programming Language :: Python
Classifier: Programming Language :: Python :: 3
Classifier: Programming Language :: Python :: 3.10
Classifier: Programming Language :: Python :: 3.11
Classifier: Programming Language :: Python :: 3.10
Classifier: Programming Language :: Python :: 3.11
Classifier: Topic :: Internet
Classifier: Topic :: Software Development :: Libraries :: Application Frameworks
Requires-Dist: click (>=8.1.3,<9.0.0)
Requires-Dist: requests (>=2.28.2,<3.0.0)
Requires-Dist: scaleway (>=0.7,<0.15)
Requires-Dist: scaleway-functions-python (>=0.2.0,<0.3.0)
Requires-Dist: typing-extensions (>=4.4.0,<5.0.0) ; python_version < "3.11"
Project-URL: Documentation, https://serverless-api-project.readthedocs.io/en/latest/
Project-URL: Repository, https://github.com/scaleway/serverless-api-framework-python
